dicom_mcp_server/__init__.py
dicom_mcp_server/server.py
dicom_mcp_server-0.1.0.dist-info/METADATA
dicom_mcp_server-0.1.0.dist-info/WHEEL
dicom_mcp_server-0.1.0.dist-info/entry_points.txt
dicom_mcp_server-0.1.0.dist-info/RECORD
