Metadata-Version: 2.4
Name: dicom-mcp-server
Version: 0.1.0
Summary: Add your description here
Author-email: yeongseo <yeongseo_park@tmax.co.kr>
Requires-Python: >=3.11
Requires-Dist: annotated-types==0.7.0
Requires-Dist: anyio==4.9.0
Requires-Dist: build>=1.2.2.post1
Requires-Dist: certifi==2025.4.26
Requires-Dist: charset-normalizer==3.4.2
Requires-Dist: click==8.2.0
Requires-Dist: h11==0.16.0
Requires-Dist: httpcore==1.0.9
Requires-Dist: httpx-sse==0.4.0
Requires-Dist: httpx==0.28.1
Requires-Dist: idna==3.10
Requires-Dist: mcp==1.9.0
Requires-Dist: pydantic-core==2.33.2
Requires-Dist: pydantic-settings==2.9.1
Requires-Dist: pydantic==2.11.4
Requires-Dist: pydicom==2.4.4
Requires-Dist: pynetdicom==2.1.1
Requires-Dist: python-dotenv==1.1.0
Requires-Dist: python-multipart==0.0.20
Requires-Dist: requests==2.32.3
Requires-Dist: sniffio==1.3.1
Requires-Dist: sse-starlette==2.3.5
Requires-Dist: starlette==0.46.2
Requires-Dist: twine>=6.1.0
Requires-Dist: typing-extensions==4.13.2
Requires-Dist: typing-inspection==0.4.0
Requires-Dist: urllib3==2.4.0
Requires-Dist: uvicorn==0.34.2
